{
  "$schema": "https://ui.shadcn.com/schema/registry-item.json",
  "name": "nova-qrbutton",
  "type": "registry:component",
  "title": "Nova Qrbutton",
  "description": "A nova-qrbutton component.",
  "dependencies": [
    "lucide-react"
  ],
  "registryDependencies": [],
  "files": [
    {
      "path": "src/components/ui/nova-qrbutton.tsx",
      "content": "import React, { useState } from \"react\";\nimport { QrCode } from \"lucide-react\";\n\nconst NeonQrButton = () => {\n  const [hovered, setHovered] = useState(false);\n\n  return (\n    <div\n      className=\"relative inline-block\"\n      onMouseEnter={() => setHovered(true)}\n      onMouseLeave={() => setHovered(false)}\n    >\n      {/* Soft pastel circular button */}\n      <button\n        aria-label=\"Show QR code\"\n        className=\"\n          relative rounded-full w-12 h-12\n          bg-white bg-opacity-90\n          border-2 border-indigo-300\n          shadow-[0_0_10px_3px_rgba(129,140,248,0.5)]\n          flex items-center justify-center\n          text-indigo-500\n          hover:text-indigo-400\n          transition-colors duration-300 ease-in-out\n          focus:outline-none focus:ring-2 focus:ring-indigo-300 focus:ring-offset-2\n          cursor-pointer\n          select-none\n        \"\n      >\n        <QrCode size={24} strokeWidth={2} />\n      </button>\n\n      {/* Light pastel popover card */}\n      <div\n        className={`\n          absolute left-1/2 top-full mt-3\n          w-52 h-52\n          -translate-x-1/2\n          rounded-2xl\n          bg-gradient-to-tr from-indigo-100 via-pink-100 to-purple-100\n          bg-opacity-90\n          border border-indigo-200\n          shadow-[0_0_25px_5px_rgba(129,140,248,0.4)]\n          flex items-center justify-center\n          transform origin-top\n          transition-all duration-300 ease-in-out\n          ${hovered ? \"opacity-100 scale-100 visible\" : \"opacity-0 scale-75 invisible pointer-events-none\"}\n        `}\n      >\n        <div className=\"bg-white bg-opacity-80 rounded-xl p-6 flex items-center justify-center\">\n          <QrCode size={128} strokeWidth={2} className=\"text-indigo-500\" />\n        </div>\n      </div>\n    </div>\n  );\n};\n\nNeonQrButton.displayName = \"NeonQrButton\";\n\nexport { NeonQrButton };\n",
      "type": "registry:component"
    }
  ],
  "_meta": {
    "author": "ruixen.ui",
    "slug": "nova-qrbutton",
    "registry_url": "https://21st.dev/r/ruixen.ui/nova-qrbutton",
    "title": "NovaQRButton",
    "description": "Ruixen Nova is a modern, glowing UI button component designed for sleek and high-performance web interfaces. With animated radial and conic gradients, this button brings a soft, dynamic glow effect that draws user attention without being distracting. Built using React and Tailwind CSS, it supports full customization including color, speed, and element type (as prop), making it highly flexible for any design system. Perfect for call-to-actions, modals, or hero sections, Ruixen Nova blends beauty with functionality and elevates your interface with a premium, futuristic feel.",
    "category": "button",
    "category_group": "UI Components",
    "downloads": 11,
    "likes": 0
  }
}