{
  "$schema": "https://ui.shadcn.com/schema/registry-item.json",
  "name": "particle-text-effect",
  "type": "registry:component",
  "title": "Particle Text Effect",
  "description": "A particle-text-effect component.",
  "dependencies": [],
  "registryDependencies": [],
  "files": [
    {
      "path": "src/components/ui/particle-text-effect.tsx",
      "content": "\"use client\"\n\nimport { useEffect, useRef } from \"react\"\n\ninterface Vector2D {\n  x: number\n  y: number\n}\n\nclass Particle {\n  pos: Vector2D = { x: 0, y: 0 }\n  vel: Vector2D = { x: 0, y: 0 }\n  acc: Vector2D = { x: 0, y: 0 }\n  target: Vector2D = { x: 0, y: 0 }\n\n  closeEnoughTarget = 100\n  maxSpeed = 1.0\n  maxForce = 0.1\n  particleSize = 10\n  isKilled = false\n\n  startColor = { r: 0, g: 0, b: 0 }\n  targetColor = { r: 0, g: 0, b: 0 }\n  colorWeight = 0\n  colorBlendRate = 0.01\n\n  move() {\n    // Check if particle is close enough to its target to slow down\n    let proximityMult = 1\n    const distance = Math.sqrt(Math.pow(this.pos.x - this.target.x, 2) + Math.pow(this.pos.y - this.target.y, 2))\n\n    if (distance < this.closeEnoughTarget) {\n      proximityMult = distance / this.closeEnoughTarget\n    }\n\n    // Add force towards target\n    const towardsTarget = {\n      x: this.target.x - this.pos.x,\n      y: this.target.y - this.pos.y,\n    }\n\n    const magnitude = Math.sqrt(towardsTarget.x * towardsTarget.x + towardsTarget.y * towardsTarget.y)\n    if (magnitude > 0) {\n      towardsTarget.x = (towardsTarget.x / magnitude) * this.maxSpeed * proximityMult\n      towardsTarget.y = (towardsTarget.y / magnitude) * this.maxSpeed * proximityMult\n    }\n\n    const steer = {\n      x: towardsTarget.x - this.vel.x,\n      y: towardsTarget.y - this.vel.y,\n    }\n\n    const steerMagnitude = Math.sqrt(steer.x * steer.x + steer.y * steer.y)\n    if (steerMagnitude > 0) {\n      steer.x = (steer.x / steerMagnitude) * this.maxForce\n      steer.y = (steer.y / steerMagnitude) * this.maxForce\n    }\n\n    this.acc.x += steer.x\n    this.acc.y += steer.y\n\n    // Move particle\n    this.vel.x += this.acc.x\n    this.vel.y += this.acc.y\n    this.pos.x += this.vel.x\n    this.pos.y += this.vel.y\n    this.acc.x = 0\n    this.acc.y = 0\n  }\n\n  draw(ctx: CanvasRenderingContext2D, drawAsPoints: boolean) {\n    // Blend towards target color\n    if (this.colorWeight < 1.0) {\n      this.colorWeight = Math.min(this.colorWeight + this.colorBlendRate, 1.0)\n    }\n\n    // Calculate current color\n    const currentColor = {\n      r: Math.round(this.startColor.r + (this.targetColor.r - this.startColor.r) * this.colorWeight),\n      g: Math.round(this.startColor.g + (this.targetColor.g - this.startColor.g) * this.colorWeight),\n      b: Math.round(this.startColor.b + (this.targetColor.b - this.startColor.b) * this.colorWeight),\n    }\n\n    if (drawAsPoints) {\n      ctx.fillStyle = `rgb(${currentColor.r}, ${currentColor.g}, ${currentColor.b})`\n      ctx.fillRect(this.pos.x, this.pos.y, 2, 2)\n    } else {\n      ctx.fillStyle = `rgb(${currentColor.r}, ${currentColor.g}, ${currentColor.b})`\n      ctx.beginPath()\n      ctx.arc(this.pos.x, this.pos.y, this.particleSize / 2, 0, Math.PI * 2)\n      ctx.fill()\n    }\n  }\n\n  kill(width: number, height: number) {\n    if (!this.isKilled) {\n      // Set target outside the scene\n      const randomPos = this.generateRandomPos(width / 2, height / 2, (width + height) / 2)\n      this.target.x = randomPos.x\n      this.target.y = randomPos.y\n\n      // Begin blending color to black\n      this.startColor = {\n        r: this.startColor.r + (this.targetColor.r - this.startColor.r) * this.colorWeight,\n        g: this.startColor.g + (this.targetColor.g - this.startColor.g) * this.colorWeight,\n        b: this.startColor.b + (this.targetColor.b - this.startColor.b) * this.colorWeight,\n      }\n      this.targetColor = { r: 0, g: 0, b: 0 }\n      this.colorWeight = 0\n\n      this.isKilled = true\n    }\n  }\n\n  private generateRandomPos(x: number, y: number, mag: number): Vector2D {\n    const randomX = Math.random() * 1000\n    const randomY = Math.random() * 500\n\n    const direction = {\n      x: randomX - x,\n      y: randomY - y,\n    }\n\n    const magnitude = Math.sqrt(direction.x * direction.x + direction.y * direction.y)\n    if (magnitude > 0) {\n      direction.x = (direction.x / magnitude) * mag\n      direction.y = (direction.y / magnitude) * mag\n    }\n\n    return {\n      x: x + direction.x,\n      y: y + direction.y,\n    }\n  }\n}\n\ninterface ParticleTextEffectProps {\n  words?: string[]\n}\n\nconst DEFAULT_WORDS = [\"HELLO\", \"21st.dev\", \"ParticleTextEffect\", \"BY\", \"KAINXU\"]\n\nexport function ParticleTextEffect({ words = DEFAULT_WORDS }: ParticleTextEffectProps) {\n  const canvasRef = useRef<HTMLCanvasElement>(null)\n  const animationRef = useRef<number>()\n  const particlesRef = useRef<Particle[]>([])\n  const frameCountRef = useRef(0)\n  const wordIndexRef = useRef(0)\n  const mouseRef = useRef({ x: 0, y: 0, isPressed: false, isRightClick: false })\n\n  const pixelSteps = 6\n  const drawAsPoints = true\n\n  const generateRandomPos = (x: number, y: number, mag: number): Vector2D => {\n    const randomX = Math.random() * 1000\n    const randomY = Math.random() * 500\n\n    const direction = {\n      x: randomX - x,\n      y: randomY - y,\n    }\n\n    const magnitude = Math.sqrt(direction.x * direction.x + direction.y * direction.y)\n    if (magnitude > 0) {\n      direction.x = (direction.x / magnitude) * mag\n      direction.y = (direction.y / magnitude) * mag\n    }\n\n    return {\n      x: x + direction.x,\n      y: y + direction.y,\n    }\n  }\n\n  const nextWord = (word: string, canvas: HTMLCanvasElement) => {\n    // const ctx = canvas.getContext(\"2d\")!\n\n    // Create off-screen canvas for text rendering\n    const offscreenCanvas = document.createElement(\"canvas\")\n    offscreenCanvas.width = canvas.width\n    offscreenCanvas.height = canvas.height\n    const offscreenCtx = offscreenCanvas.getContext(\"2d\")!\n\n    // Draw text\n    offscreenCtx.fillStyle = \"white\"\n    offscreenCtx.font = \"bold 100px Arial\"\n    offscreenCtx.textAlign = \"center\"\n    offscreenCtx.textBaseline = \"middle\"\n    offscreenCtx.fillText(word, canvas.width / 2, canvas.height / 2)\n\n    const imageData = offscreenCtx.getImageData(0, 0, canvas.width, canvas.height)\n    const pixels = imageData.data\n\n    // Generate new color\n    const newColor = {\n      r: Math.random() * 255,\n      g: Math.random() * 255,\n      b: Math.random() * 255,\n    }\n\n    const particles = particlesRef.current\n    let particleIndex = 0\n\n    // Collect coordinates\n    const coordsIndexes: number[] = []\n    for (let i = 0; i < pixels.length; i += pixelSteps * 4) {\n      coordsIndexes.push(i)\n    }\n\n    // Shuffle coordinates for fluid motion\n    for (let i = coordsIndexes.length - 1; i > 0; i--) {\n      const j = Math.floor(Math.random() * (i + 1))\n      ;[coordsIndexes[i], coordsIndexes[j]] = [coordsIndexes[j], coordsIndexes[i]]\n    }\n\n    for (const coordIndex of coordsIndexes) {\n      const pixelIndex = coordIndex\n      const alpha = pixels[pixelIndex + 3]\n\n      if (alpha > 0) {\n        const x = (pixelIndex / 4) % canvas.width\n        const y = Math.floor(pixelIndex / 4 / canvas.width)\n\n        let particle: Particle\n\n        if (particleIndex < particles.length) {\n          particle = particles[particleIndex]\n          particle.isKilled = false\n          particleIndex++\n        } else {\n          particle = new Particle()\n\n          const randomPos = generateRandomPos(canvas.width / 2, canvas.height / 2, (canvas.width + canvas.height) / 2)\n          particle.pos.x = randomPos.x\n          particle.pos.y = randomPos.y\n\n          particle.maxSpeed = Math.random() * 6 + 4\n          particle.maxForce = particle.maxSpeed * 0.05\n          particle.particleSize = Math.random() * 6 + 6\n          particle.colorBlendRate = Math.random() * 0.0275 + 0.0025\n\n          particles.push(particle)\n        }\n\n        // Set color transition\n        particle.startColor = {\n          r: particle.startColor.r + (particle.targetColor.r - particle.startColor.r) * particle.colorWeight,\n          g: particle.startColor.g + (particle.targetColor.g - particle.startColor.g) * particle.colorWeight,\n          b: particle.startColor.b + (particle.targetColor.b - particle.startColor.b) * particle.colorWeight,\n        }\n        particle.targetColor = newColor\n        particle.colorWeight = 0\n\n        particle.target.x = x\n        particle.target.y = y\n      }\n    }\n\n    // Kill remaining particles\n    for (let i = particleIndex; i < particles.length; i++) {\n      particles[i].kill(canvas.width, canvas.height)\n    }\n  }\n\n  const animate = () => {\n    const canvas = canvasRef.current\n    if (!canvas) return\n\n    const ctx = canvas.getContext(\"2d\")!\n    const particles = particlesRef.current\n\n    // Background with motion blur\n    ctx.fillStyle = \"rgba(0, 0, 0, 0.1)\"\n    ctx.fillRect(0, 0, canvas.width, canvas.height)\n\n    // Update and draw particles\n    for (let i = particles.length - 1; i >= 0; i--) {\n      const particle = particles[i]\n      particle.move()\n      particle.draw(ctx, drawAsPoints)\n\n      // Remove dead particles that are out of bounds\n      if (particle.isKilled) {\n        if (\n          particle.pos.x < 0 ||\n          particle.pos.x > canvas.width ||\n          particle.pos.y < 0 ||\n          particle.pos.y > canvas.height\n        ) {\n          particles.splice(i, 1)\n        }\n      }\n    }\n\n    // Handle mouse interaction\n    if (mouseRef.current.isPressed && mouseRef.current.isRightClick) {\n      particles.forEach((particle) => {\n        const distance = Math.sqrt(\n          Math.pow(particle.pos.x - mouseRef.current.x, 2) + Math.pow(particle.pos.y - mouseRef.current.y, 2),\n        )\n        if (distance < 50) {\n          particle.kill(canvas.width, canvas.height)\n        }\n      })\n    }\n\n    // Auto-advance words\n    frameCountRef.current++\n    if (frameCountRef.current % 240 === 0) {\n      wordIndexRef.current = (wordIndexRef.current + 1) % words.length\n      nextWord(words[wordIndexRef.current], canvas)\n    }\n\n    animationRef.current = requestAnimationFrame(animate)\n  }\n\n  useEffect(() => {\n    const canvas = canvasRef.current\n    if (!canvas) return\n\n    canvas.width = 1000\n    canvas.height = 500\n\n    // Initialize with first word\n    nextWord(words[0], canvas)\n\n    // Start animation\n    animate()\n\n    // Mouse event handlers\n    const handleMouseDown = (e: MouseEvent) => {\n      mouseRef.current.isPressed = true\n      mouseRef.current.isRightClick = e.button === 2\n      const rect = canvas.getBoundingClientRect()\n      mouseRef.current.x = e.clientX - rect.left\n      mouseRef.current.y = e.clientY - rect.top\n    }\n\n    const handleMouseUp = () => {\n      mouseRef.current.isPressed = false\n      mouseRef.current.isRightClick = false\n    }\n\n    const handleMouseMove = (e: MouseEvent) => {\n      const rect = canvas.getBoundingClientRect()\n      mouseRef.current.x = e.clientX - rect.left\n      mouseRef.current.y = e.clientY - rect.top\n    }\n\n    const handleContextMenu = (e: MouseEvent) => {\n      e.preventDefault()\n    }\n\n    canvas.addEventListener(\"mousedown\", handleMouseDown)\n    canvas.addEventListener(\"mouseup\", handleMouseUp)\n    canvas.addEventListener(\"mousemove\", handleMouseMove)\n    canvas.addEventListener(\"contextmenu\", handleContextMenu)\n\n    return () => {\n      if (animationRef.current) {\n        cancelAnimationFrame(animationRef.current)\n      }\n      canvas.removeEventListener(\"mousedown\", handleMouseDown)\n      canvas.removeEventListener(\"mouseup\", handleMouseUp)\n      canvas.removeEventListener(\"mousemove\", handleMouseMove)\n      canvas.removeEventListener(\"contextmenu\", handleContextMenu)\n    }\n  }, [])\n\n  return (\n    <div className=\"flex flex-col items-center justify-center min-h-screen bg-black p-4\">\n      <canvas\n        ref={canvasRef}\n        className=\"border border-gray-800 rounded-lg shadow-2xl\"\n        style={{ maxWidth: \"100%\", height: \"auto\" }}\n      />\n      <div className=\"mt-4 text-white text-sm text-center max-w-md\">\n        <p className=\"mb-2\">Particle Text Effect</p>\n        <p className=\"text-gray-400 text-xs\">\n          Right-click and hold while moving mouse to destroy particles • Words change automatically every 4 seconds\n        </p>\n      </div>\n    </div>\n  )\n}\n",
      "type": "registry:component"
    }
  ],
  "_meta": {
    "author": "xubohuah",
    "slug": "particle-text-effect",
    "registry_url": "https://21st.dev/r/xubohuah/particle-text-effect",
    "title": "ParticleTextEffect",
    "description": "A dynamic text animation component that renders words using interactive particles with fluid motion and color transitions, allowing particle destruction through right-click mouse interaction.",
    "category": "background",
    "category_group": "Marketing Blocks",
    "downloads": 1091,
    "likes": 0
  }
}