{
  "$schema": "https://ui.shadcn.com/schema/registry-item.json",
  "name": "avatar-group",
  "type": "registry:component",
  "title": "Avatar Group",
  "description": "A avatar-group component.",
  "dependencies": [
    "next",
    "framer-motion"
  ],
  "registryDependencies": [],
  "files": [
    {
      "path": "src/components/ui/avatar-group.tsx",
      "content": "\"use client\";\nimport Image from \"next/image\";\nimport React, { useState } from \"react\";\nimport { motion, AnimatePresence } from \"framer-motion\";\nimport { cn } from \"@/lib/utils\";\n\ninterface AvatarItem {\n  id: number;\n  name: string;\n  designation: string;\n  image: string;\n}\n\ninterface AvatarGroupProps {\n  items: AvatarItem[];\n  className?: string;\n  maxVisible?: number;\n  size?: \"sm\" | \"md\" | \"lg\";\n}\n\n// Individual Avatar Component\nconst Avatar = ({\n  item,\n  index,\n  totalItems,\n  size,\n  isHovered,\n  onHover,\n  onLeave,\n}: {\n  item: AvatarItem;\n  index: number;\n  totalItems: number;\n  size: \"sm\" | \"md\" | \"lg\";\n  isHovered: boolean;\n  onHover: () => void;\n  onLeave: () => void;\n}) => {\n  const sizeClasses = {\n    sm: \"h-8 w-8\",\n    md: \"h-10 w-10\",\n    lg: \"h-12 w-12\",\n  };\n\n  return (\n    <div\n      className=\"relative group flex items-center justify-center\"\n      onMouseEnter={onHover}\n      onMouseLeave={onLeave}\n      style={{\n        marginLeft: index === 0 ? 0 : \"-0.5rem\",\n        zIndex: totalItems - index,\n      }}\n    >\n      <AnimatePresence mode=\"popLayout\">\n        {isHovered && (\n          <motion.div\n            initial={{ opacity: 0, y: 10, scale: 0.95 }}\n            animate={{\n              opacity: 1,\n              y: 0,\n              scale: 1,\n              transition: {\n                type: \"spring\",\n                stiffness: 200,\n                damping: 20,\n              },\n            }}\n            exit={{ opacity: 0, y: 10, scale: 0.95 }}\n            className=\"absolute -top-16 whitespace-nowrap flex text-xs flex-col items-center justify-center rounded-xl bg-white z-50 shadow-lg px-4 py-2 border min-w-max\"\n          >\n            <div className=\"font-bold text-gray-900 relative z-30 text-base text-center\">\n              {item.name}\n            </div>\n            <div className=\"text-gray-600 text-xs text-center\">\n              {item.designation}\n            </div>\n          </motion.div>\n        )}\n      </AnimatePresence>\n\n      <motion.div\n        whileHover={{ scale: 1.05, zIndex: 100 }}\n        transition={{ type: \"spring\", stiffness: 200, damping: 15 }}\n        className=\"relative\"\n      >\n        <Image\n          height={100}\n          width={100}\n          src={item.image}\n          alt={item.name}\n          className={cn(\n            \"object-cover !rounded-full border-2 border-background transition duration-300\",\n            sizeClasses[size]\n          )}\n        />\n      </motion.div>\n    </div>\n  );\n};\n\nconst AvatarGroup = ({\n  items,\n  className,\n  maxVisible = 5,\n  size = \"md\",\n}: AvatarGroupProps) => {\n  const [hoveredIndex, setHoveredIndex] = useState<number | null>(null);\n\n  const visibleItems = items.slice(0, maxVisible);\n  const remainingCount = items.length - maxVisible;\n\n  return (\n    <div className={cn(\"flex items-center justify-center\", className)}>\n      {visibleItems.map((item, index) => (\n        <Avatar\n          key={item.id}\n          item={item}\n          index={index}\n          totalItems={visibleItems.length}\n          size={size}\n          isHovered={hoveredIndex === item.id}\n          onHover={() => setHoveredIndex(item.id)}\n          onLeave={() => setHoveredIndex(null)}\n        />\n      ))}\n\n      {remainingCount > 0 && (\n        <motion.div\n          initial={{ opacity: 0, scale: 0.9 }}\n          animate={{ opacity: 1, scale: 1 }}\n          className={cn(\n            \"flex items-center justify-center rounded-full border-2 border-background bg-muted text-muted-foreground font-medium\",\n            size === \"sm\"\n              ? \"h-8 w-8\"\n              : size === \"md\"\n              ? \"h-10 w-10\"\n              : \"h-12 w-12\",\n            \"ml-[-0.5rem]\"\n          )}\n        >\n          +{remainingCount}\n        </motion.div>\n      )}\n    </div>\n  );\n};\n\nexport default AvatarGroup;\n",
      "type": "registry:component"
    }
  ],
  "_meta": {
    "author": "chetanverma16",
    "slug": "avatar-group",
    "registry_url": "https://21st.dev/r/chetanverma16/avatar-group",
    "title": "Avatar Group",
    "description": "An avatar group component made with framer-motion and Tailwind CSS",
    "category": "avatar",
    "category_group": "UI Components",
    "downloads": 271,
    "likes": 0
  }
}